class_d/__init__.py
class_d_oliversandli-0.0.1.data/scripts/class_d
class_d_oliversandli-0.0.1.dist-info/LICENSE
class_d_oliversandli-0.0.1.dist-info/METADATA
class_d_oliversandli-0.0.1.dist-info/WHEEL
class_d_oliversandli-0.0.1.dist-info/top_level.txt
class_d_oliversandli-0.0.1.dist-info/RECORD
