Metadata-Version: 2.1
Name: class-d-oliversandli
Version: 0.0.1
Summary: Get a license from the GitHub API
Home-page: https://github.com/oliversandli/class_d
Author: Oliver Sandli
Author-email: racerpingpong@gmail.com
License: UNKNOWN
Platform: UNKNOWN
Classifier: Programming Language :: Python :: 3
Classifier: License :: OSI Approved :: MIT License
Classifier: Operating System :: Unix
Requires-Python: >=3.6
Requires-Dist: inquirer
Requires-Dist: requests
